{
  "mcpServers": {
    "deepwiki": {
      "type": "http",
      "url": "https://mcp.deepwiki.com/mcp"
    },
    "grep": {
      "type": "http",
      "url": "https://mcp.grep.app"
    },
    "infisical": {
      "type": "stdio",
      "command": "npx",
      "args": [
        "@infisical/mcp@latest"
      ],
      "env": {}
    },
    "context7": {
      "type": "http",
      "url": "https://mcp.context7.com/mcp"
    },
    "firecrawl": {
      "type": "stdio",
      "command": "npx",
      "args": [
        "firecrawl-mcp"
      ]
    },
    "netdata": {
      "type": "stdio",
      "command": "/usr/local/netdata/usr/sbin/nd-mcp",
      "args": [
        "ws://192.168.10.02:19999/mcp?api_key=d8d22964-c41e-43ab-bdba-11c063622051"
      ]
    }
  }
}